posecheck/__init__.py
posecheck/docking_eval.py
posecheck/eval.py
posecheck/posecheck.py
posecheck/data/__init__.py
posecheck/data/datasets.py
posecheck/utils/__init__.py
posecheck/utils/biopython.py
posecheck/utils/chem.py
posecheck/utils/clashes.py
posecheck/utils/constants.py
posecheck/utils/docking.py
posecheck/utils/docking_utils.py
posecheck/utils/interactions.py
posecheck/utils/loading.py
posecheck/utils/strain.py
posecheck/utils/validators.py
posecheck-1.3.1.dist-info/LICENSE
posecheck-1.3.1.dist-info/METADATA
posecheck-1.3.1.dist-info/WHEEL
posecheck-1.3.1.dist-info/top_level.txt
posecheck-1.3.1.dist-info/RECORD
