Metadata-Version: 2.1
Name: posecheck
Version: 1.3.1
Summary: A library for benchmarking poses of 3D SBDD models
Author: Charles Harris
Author-email: cch57@cam.ac.uk
Classifier: Development Status :: 3 - Alpha
Classifier: Intended Audience :: Science/Research
Classifier: Topic :: Scientific/Engineering :: Bio-Informatics
Classifier: License :: OSI Approved :: MIT License
Classifier: Programming Language :: Python :: 3.8
Classifier: Programming Language :: Python :: 3.9
Classifier: Programming Language :: Python :: 3.10
License-File: LICENSE
Requires-Dist: rdkit
Requires-Dist: prolif
Requires-Dist: datamol
Requires-Dist: hydride
Requires-Dist: biopython
Requires-Dist: pandas ==2.0.0
Requires-Dist: seaborn
Requires-Dist: matplotlib
Requires-Dist: numpy
